convection/plugins/secrets/generic.py
convection/plugins/secrets/specs/plugin.secret.generic.spec
convection_plugin_secrets_generic-1.0.0.dist-info/LICENSE.md
convection_plugin_secrets_generic-1.0.0.dist-info/METADATA
convection_plugin_secrets_generic-1.0.0.dist-info/WHEEL
convection_plugin_secrets_generic-1.0.0.dist-info/top_level.txt
convection_plugin_secrets_generic-1.0.0.dist-info/RECORD
